{
  "required": true,
  "package": "me.Thelnfamous1.joyofpaintingextras.mixin",
  "compatibilityLevel": "JAVA_17",
  "refmap": "joyofpaintingextras.refmap.json",
  "mixins": [
    "CanvasTypeExtender",
    "CommandImportMixin",
    "EntityCanvasMixin",
    "EntityEaselMixin",
    "ItemCanvasAccessor",
    "ItemCanvasMixin",
    "ItemMixin"
  ],
  "client": [
    "BasePaletteAccessor",
    "BasePaletteMixin",
    "CanvasItemRendererMixin",
    "EaselCanvasLayerMixin",
    "GuiCanvasEditMixin",
    "GuiCanvasViewMixin"
  ],
  "minVersion": "0.8.5"
}
